Metadata-Version: 2.4
Name: dramatiq
Version: 2.0.1
Summary: Background Processing for Python 3.
Author: Bogdan Popa
Author-email: bogdan@cleartype.io
Project-URL: Documentation, https://dramatiq.io
Project-URL: Changelog, https://dramatiq.io/changelog.html
Project-URL: Source, https://github.com/Bogdanp/dramatiq
Classifier: Programming Language :: Python :: 3.10
Classifier: Programming Language :: Python :: 3.11
Classifier: Programming Language :: Python :: 3.12
Classifier: Programming Language :: Python :: 3.13
Classifier: Programming Language :: Python :: 3.14
Classifier: Programming Language :: Python :: 3 :: Only
Classifier: Topic :: System :: Distributed Computing
Classifier: License :: OSI Approved :: GNU Lesser General Public License v3 or later (LGPLv3+)
Requires-Python: >=3.10
License-File: COPYING
License-File: COPYING.LESSER
Provides-Extra: gevent
Requires-Dist: gevent>=1.1; extra == "gevent"
Provides-Extra: memcached
Requires-Dist: pylibmc<2.0,>=1.5; extra == "memcached"
Provides-Extra: prometheus
Requires-Dist: prometheus-client>=0.2; extra == "prometheus"
Provides-Extra: rabbitmq
Requires-Dist: pika<2.0,>=1.0; extra == "rabbitmq"
Provides-Extra: redis
Requires-Dist: redis<7.0,>=4.0; extra == "redis"
Provides-Extra: watch
Requires-Dist: watchdog>=4.0; extra == "watch"
Requires-Dist: watchdog_gevent>=0.2; extra == "watch"
Provides-Extra: all
Requires-Dist: watchdog>=4.0; extra == "all"
Requires-Dist: redis<7.0,>=4.0; extra == "all"
Requires-Dist: gevent>=1.1; extra == "all"
Requires-Dist: pylibmc<2.0,>=1.5; extra == "all"
Requires-Dist: prometheus-client>=0.2; extra == "all"
Requires-Dist: watchdog_gevent>=0.2; extra == "all"
Requires-Dist: pika<2.0,>=1.0; extra == "all"
Dynamic: author
Dynamic: author-email
Dynamic: classifier
Dynamic: description
Dynamic: description-content-type
Dynamic: license-file
Dynamic: project-url
Dynamic: provides-extra
Dynamic: requires-python
Dynamic: summary
